scratchattach/__init__.py
scratchattach/cloud/__init__.py
scratchattach/cloud/_base.py
scratchattach/cloud/cloud.py
scratchattach/editor/__init__.py
scratchattach/editor/asset.py
scratchattach/editor/backpack_json.py
scratchattach/editor/base.py
scratchattach/editor/block.py
scratchattach/editor/blockshape.py
scratchattach/editor/build_defaulting.py
scratchattach/editor/comment.py
scratchattach/editor/commons.py
scratchattach/editor/extension.py
scratchattach/editor/field.py
scratchattach/editor/inputs.py
scratchattach/editor/meta.py
scratchattach/editor/monitor.py
scratchattach/editor/mutation.py
scratchattach/editor/pallete.py
scratchattach/editor/prim.py
scratchattach/editor/project.py
scratchattach/editor/sbuild.py
scratchattach/editor/sprite.py
scratchattach/editor/twconfig.py
scratchattach/editor/vlb.py
scratchattach/eventhandlers/__init__.py
scratchattach/eventhandlers/_base.py
scratchattach/eventhandlers/cloud_events.py
scratchattach/eventhandlers/cloud_recorder.py
scratchattach/eventhandlers/cloud_requests.py
scratchattach/eventhandlers/cloud_server.py
scratchattach/eventhandlers/cloud_storage.py
scratchattach/eventhandlers/combine.py
scratchattach/eventhandlers/filterbot.py
scratchattach/eventhandlers/message_events.py
scratchattach/other/__init__.py
scratchattach/other/other_apis.py
scratchattach/other/project_json_capabilities.py
scratchattach/site/__init__.py
scratchattach/site/_base.py
scratchattach/site/activity.py
scratchattach/site/backpack_asset.py
scratchattach/site/browser_cookies.py
scratchattach/site/classroom.py
scratchattach/site/cloud_activity.py
scratchattach/site/comment.py
scratchattach/site/forum.py
scratchattach/site/project.py
scratchattach/site/session.py
scratchattach/site/studio.py
scratchattach/site/user.py
scratchattach/utils/__init__.py
scratchattach/utils/commons.py
scratchattach/utils/encoder.py
scratchattach/utils/enums.py
scratchattach/utils/exceptions.py
scratchattach/utils/requests.py
scratchattach-2.1.13.dist-info/licenses/LICENSE
scratchattach-2.1.13.dist-info/METADATA
scratchattach-2.1.13.dist-info/WHEEL
scratchattach-2.1.13.dist-info/top_level.txt
scratchattach-2.1.13.dist-info/RECORD
