Metadata-Version: 2.4
Name: scratchattach
Version: 2.1.13
Summary: A Scratch API Wrapper
Home-page: https://scratchattach.tim1de.net
Author: TimMcCool
Author-email: 
Keywords: scratch api,scratchattach,scratch api python,scratch python,scratch for python,scratch,scratch cloud,scratch cloud variables,scratch bot
Classifier: Development Status :: 5 - Production/Stable
Classifier: Intended Audience :: Developers
Classifier: Programming Language :: Python :: 3
Classifier: Operating System :: Unix
Classifier: Operating System :: MacOS :: MacOS X
Classifier: Operating System :: Microsoft :: Windows
License-File: LICENSE
Requires-Dist: websocket-client
Requires-Dist: requests
Requires-Dist: bs4
Requires-Dist: SimpleWebSocketServer
Requires-Dist: typing-extensions
Dynamic: author
Dynamic: classifier
Dynamic: description
Dynamic: description-content-type
Dynamic: home-page
Dynamic: keywords
Dynamic: license-file
Dynamic: requires-dist
Dynamic: summary
